AUTHORS.rst
CONTRIBUTING.rst
HISTORY.rst
LICENSE
MANIFEST.in
README.rst
setup.cfg
setup.py
docs/Makefile
docs/authors.rst
docs/conf.py
docs/contributing.rst
docs/history.rst
docs/index.rst
docs/installation.rst
docs/make.bat
docs/modules.rst
docs/pybaby.rst
docs/readme.rst
docs/usage.rst
docs/_build/html/_static/ajax-loader.gif
docs/_build/html/_static/comment-bright.png
docs/_build/html/_static/comment-close.png
docs/_build/html/_static/comment.png
docs/_build/html/_static/down-pressed.png
docs/_build/html/_static/down.png
docs/_build/html/_static/file.png
docs/_build/html/_static/minus.png
docs/_build/html/_static/plus.png
docs/_build/html/_static/up-pressed.png
docs/_build/html/_static/up.png
pybaby/__init__.py
pybaby/cli.py
pybaby/pybaby.py
pybaby.egg-info/PKG-INFO
pybaby.egg-info/SOURCES.txt
pybaby.egg-info/dependency_links.txt
pybaby.egg-info/entry_points.txt
pybaby.egg-info/not-zip-safe
pybaby.egg-info/requires.txt
pybaby.egg-info/top_level.txt
tests/test_pybaby.py