Metadata-Version: 1.1
Name: pybaby
Version: 0.1.1
Summary: A Python baby package
Home-page: https://github.com/goanpeca/pybaby
Author: Gonzalo Pena-Castellanos
Author-email: goanpeca@gmail.com
License: MIT license
Keywords: pybaby
Platform: UNKNOWN
Classifier: Development Status :: 2 - Pre-Alpha
Classifier: Intended Audience :: Developers
Classifier: License :: OSI Approved :: MIT License
Classifier: Natural Language :: English
Classifier: Programming Language :: Python :: 2
Classifier: Programming Language :: Python :: 2.7
Classifier: Programming Language :: Python :: 3
Classifier: Programming Language :: Python :: 3.4
Classifier: Programming Language :: Python :: 3.5
Classifier: Programming Language :: Python :: 3.6
